jackpy/__init__.py
jackpy/internal.py
jackpy/jack.py
jackpy/msf.py
jackpolynomials-0.1.0.dist-info/LICENSE
jackpolynomials-0.1.0.dist-info/WHEEL
jackpolynomials-0.1.0.dist-info/METADATA
jackpolynomials-0.1.0.dist-info/RECORD
